README
marie.py
setup.py
Marie.egg-info/PKG-INFO
Marie.egg-info/SOURCES.txt
Marie.egg-info/dependency_links.txt
Marie.egg-info/top_level.txt