Metadata-Version: 1.0
Name: Marie
Version: 1.0.5
Summary: A WSGI micro-framework for websites in Python
Home-page: http://www.trydyingtolive.com/marie/
Author: Mark W. Lee
Author-email: trydyingtolive@gmail.com
License: GPLv3
Keywords: Marie,WSGI,micro,framework,Redis,Mako
Platform: UNKNOWN
Classifier: Development Status :: 5 - Production/Stable
Classifier: Environment :: Console
Classifier: Intended Audience :: Developers
Classifier: License :: OSI Approved :: GNU General Public License (GPL)
Classifier: Operating System :: OS Independent
Classifier: Programming Language :: Python
